LICENSE.txt
MANIFEST.in
README.rst
requirements.txt
setup.py
chest/__init__.py
chest/_version.py
chest/core.py
chest/utils.py
chest.egg-info/PKG-INFO
chest.egg-info/SOURCES.txt
chest.egg-info/dependency_links.txt
chest.egg-info/not-zip-safe
chest.egg-info/requires.txt
chest.egg-info/top_level.txt
chest/tests/test_core.py
chest/tests/test_utils.py