Metadata-Version: 1.0
Name: chest
Version: 0.2.2
Summary: Simple on-disk dictionary
Home-page: https://github.com/ContinuumIO/chest
Author: Matthew Rocklin
Author-email: mrocklin@gmail.com
License: BSD
Keywords: dictionary out-of-core
Platform: UNKNOWN
